<?xml version="1.0" encoding="utf-8"?>
<TransferHeader>
  <DataKsiegowania> </DataKsiegowania>
  <KodLokalizacjiPierwotnej>3200</KodLokalizacjiPierwotnej>
  <KodLokalizacjiDocelowej>SK59</KodLokalizacjiDocelowej>
  <KodLokalizacjiWDrodze>XMWDR</KodLokalizacjiWDrodze>
  <DataWydania> </DataWydania>
  <DataPrzyjecia> </DataPrzyjecia>
  <Status> </Status>
  <Uwagi>wysyłka : ul.Nędzy Kubińca 105 C, 34-511 Kościelisko</Uwagi>
  <NrZam>RB.27.11.19/Szpec</NrZam>
  <NrTymczasowy>3926268</NrTymczasowy>
  <TransferLine>
    <NrWiersza>10</NrWiersza>
    <NrZapasu>5001500</NrZapasu>
    <Ilosc>1</Ilosc>
    <jednostka>SZT</jednostka>
    <IloscDoWydania>1</IloscDoWydania>
    <Status> </Status>
    <Opis>Zasuwa kołnierzowa typu E1</Opis>
    <KodLokalizacjiPierwotnej>3200</KodLokalizacjiPierwotnej>
    <KodLokalizacjiDocelowej>SK59</KodLokalizacjiDocelowej>
    <KodLokalizacjiWDrodze>XMWDR</KodLokalizacjiWDrodze>
    <DataWydania> </DataWydania>
    <DataPrzyjecia> </DataPrzyjecia>
    <NrTymczasowy>3926268</NrTymczasowy>
  </TransferLine>
  <TransferLine>
    <NrWiersza>20</NrWiersza>
    <NrZapasu>5008164</NrZapasu>
    <Ilosc>1</Ilosc>
    <jednostka>SZT</jednostka>
    <IloscDoWydania>1</IloscDoWydania>
    <Status> </Status>
    <Opis>Trzpień teleskopowy 9500A</Opis>
    <KodLokalizacjiPierwotnej>3200</KodLokalizacjiPierwotnej>
    <KodLokalizacjiDocelowej>SK59</KodLokalizacjiDocelowej>
    <KodLokalizacjiWDrodze>XMWDR</KodLokalizacjiWDrodze>
    <DataWydania> </DataWydania>
    <DataPrzyjecia> </DataPrzyjecia>
    <NrTymczasowy>3926268</NrTymczasowy>
  </TransferLine>
  <TransferLine>
    <NrWiersza>30</NrWiersza>
    <NrZapasu>5003093</NrZapasu>
    <Ilosc>4</Ilosc>
    <jednostka>SZT</jednostka>
    <IloscDoWydania>4</IloscDoWydania>
    <Status> </Status>
    <Opis>Zasuwa do przyłącza domowego</Opis>
    <KodLokalizacjiPierwotnej>3200</KodLokalizacjiPierwotnej>
    <KodLokalizacjiDocelowej>SK59</KodLokalizacjiDocelowej>
    <KodLokalizacjiWDrodze>XMWDR</KodLokalizacjiWDrodze>
    <DataWydania> </DataWydania>
    <DataPrzyjecia> </DataPrzyjecia>
    <NrTymczasowy>3926268</NrTymczasowy>
  </TransferLine>
  <TransferLine>
    <NrWiersza>40</NrWiersza>
    <NrZapasu>5005389</NrZapasu>
    <Ilosc>2</Ilosc>
    <jednostka>SZT</jednostka>
    <IloscDoWydania>2</IloscDoWydania>
    <Status> </Status>
    <Opis>Złączka ISO dla rur PE, POM</Opis>
    <KodLokalizacjiPierwotnej>3200</KodLokalizacjiPierwotnej>
    <KodLokalizacjiDocelowej>SK59</KodLokalizacjiDocelowej>
    <KodLokalizacjiWDrodze>XMWDR</KodLokalizacjiWDrodze>
    <DataWydania> </DataWydania>
    <DataPrzyjecia> </DataPrzyjecia>
    <NrTymczasowy>3926268</NrTymczasowy>
  </TransferLine>
</TransferHeader>
