<?xml version="1.0" encoding="utf-8"?>
<TransferHeader>
  <DataKsiegowania> </DataKsiegowania>
  <KodLokalizacjiPierwotnej>3200</KodLokalizacjiPierwotnej>
  <KodLokalizacjiDocelowej>SK55</KodLokalizacjiDocelowej>
  <KodLokalizacjiWDrodze>XMWDR</KodLokalizacjiWDrodze>
  <DataWydania> </DataWydania>
  <DataPrzyjecia> </DataPrzyjecia>
  <Status> </Status>
  <Uwagi> </Uwagi>
  <NrZam> </NrZam>
  <NrTymczasowy>2389694</NrTymczasowy>
  <TransferLine>
    <NrWiersza>10</NrWiersza>
    <NrZapasu>5005488</NrZapasu>
    <Ilosc>20</Ilosc>
    <jednostka>SZT</jednostka>
    <IloscDoWydania>20</IloscDoWydania>
    <Status> </Status>
    <Opis>Złączka ISO dla rur PE, POM</Opis>
    <KodLokalizacjiPierwotnej>3200</KodLokalizacjiPierwotnej>
    <KodLokalizacjiDocelowej>SK55</KodLokalizacjiDocelowej>
    <KodLokalizacjiWDrodze>XMWDR</KodLokalizacjiWDrodze>
    <DataWydania> </DataWydania>
    <DataPrzyjecia> </DataPrzyjecia>
    <NrTymczasowy>2389694</NrTymczasowy>
  </TransferLine>
</TransferHeader>
