<?xml version="1.0" encoding="utf-8"?>
<TransferHeader>
  <DataKsiegowania> </DataKsiegowania>
  <KodLokalizacjiPierwotnej>3200</KodLokalizacjiPierwotnej>
  <KodLokalizacjiDocelowej>SK89</KodLokalizacjiDocelowej>
  <KodLokalizacjiWDrodze>XMWDR</KodLokalizacjiWDrodze>
  <DataWydania> </DataWydania>
  <DataPrzyjecia> </DataPrzyjecia>
  <Status> </Status>
  <Uwagi>Bardzo pilne!!!</Uwagi>
  <NrZam> </NrZam>
  <NrTymczasowy>8948520</NrTymczasowy>
  <TransferLine>
    <NrWiersza>10</NrWiersza>
    <NrZapasu>5001940</NrZapasu>
    <Ilosc>1</Ilosc>
    <jednostka>SZT</jednostka>
    <IloscDoWydania>1</IloscDoWydania>
    <Status> </Status>
    <Opis>Zasuwa kołnierzowa długa E1</Opis>
    <KodLokalizacjiPierwotnej>3200</KodLokalizacjiPierwotnej>
    <KodLokalizacjiDocelowej>SK89</KodLokalizacjiDocelowej>
    <KodLokalizacjiWDrodze>XMWDR</KodLokalizacjiWDrodze>
    <DataWydania> </DataWydania>
    <DataPrzyjecia> </DataPrzyjecia>
    <NrTymczasowy>8948520</NrTymczasowy>
  </TransferLine>
</TransferHeader>
