<?xml version="1.0" encoding="utf-8"?>
<TransferHeader>
  <DataKsiegowania> </DataKsiegowania>
  <KodLokalizacjiPierwotnej>3200</KodLokalizacjiPierwotnej>
  <KodLokalizacjiDocelowej>SK59</KodLokalizacjiDocelowej>
  <KodLokalizacjiWDrodze>XMWDR</KodLokalizacjiWDrodze>
  <DataWydania> </DataWydania>
  <DataPrzyjecia> </DataPrzyjecia>
  <Status> </Status>
  <Uwagi>WYSYŁKA:&#13;
INSTALBUD UL. NĘDZY KUBIŃCA 105C 34-511 KOŚCIELISKO /BEZ PAPIERÓW/ </Uwagi>
  <NrZam>PI:18.03.20/SZPEC/KOŚCIELISKO</NrZam>
  <NrTymczasowy>8379960</NrTymczasowy>
  <TransferLine>
    <NrWiersza>10</NrWiersza>
    <NrZapasu>5003105</NrZapasu>
    <Ilosc>4</Ilosc>
    <jednostka>SZT</jednostka>
    <IloscDoWydania>4</IloscDoWydania>
    <Status> </Status>
    <Opis>Zasuwa do przyłącza domowego</Opis>
    <KodLokalizacjiPierwotnej>3200</KodLokalizacjiPierwotnej>
    <KodLokalizacjiDocelowej>SK59</KodLokalizacjiDocelowej>
    <KodLokalizacjiWDrodze>XMWDR</KodLokalizacjiWDrodze>
    <DataWydania> </DataWydania>
    <DataPrzyjecia> </DataPrzyjecia>
    <NrTymczasowy>8379960</NrTymczasowy>
  </TransferLine>
  <TransferLine>
    <NrWiersza>30</NrWiersza>
    <NrZapasu>5003112</NrZapasu>
    <Ilosc>2</Ilosc>
    <jednostka>SZT</jednostka>
    <IloscDoWydania>2</IloscDoWydania>
    <Status> </Status>
    <Opis>Zasuwa do przyłącza domowego</Opis>
    <KodLokalizacjiPierwotnej>3200</KodLokalizacjiPierwotnej>
    <KodLokalizacjiDocelowej>SK59</KodLokalizacjiDocelowej>
    <KodLokalizacjiWDrodze>XMWDR</KodLokalizacjiWDrodze>
    <DataWydania> </DataWydania>
    <DataPrzyjecia> </DataPrzyjecia>
    <NrTymczasowy>8379960</NrTymczasowy>
  </TransferLine>
  <TransferLine>
    <NrWiersza>40</NrWiersza>
    <NrZapasu>5003108</NrZapasu>
    <Ilosc>4</Ilosc>
    <jednostka>SZT</jednostka>
    <IloscDoWydania>4</IloscDoWydania>
    <Status> </Status>
    <Opis>Zasuwa do przyłącza domowego</Opis>
    <KodLokalizacjiPierwotnej>3200</KodLokalizacjiPierwotnej>
    <KodLokalizacjiDocelowej>SK59</KodLokalizacjiDocelowej>
    <KodLokalizacjiWDrodze>XMWDR</KodLokalizacjiWDrodze>
    <DataWydania> </DataWydania>
    <DataPrzyjecia> </DataPrzyjecia>
    <NrTymczasowy>8379960</NrTymczasowy>
  </TransferLine>
  <TransferLine>
    <NrWiersza>50</NrWiersza>
    <NrZapasu>5006117</NrZapasu>
    <Ilosc>7</Ilosc>
    <jednostka>SZT</jednostka>
    <IloscDoWydania>7</IloscDoWydania>
    <Status> </Status>
    <Opis>Trójnik z odejściem gwintowym</Opis>
    <KodLokalizacjiPierwotnej>3200</KodLokalizacjiPierwotnej>
    <KodLokalizacjiDocelowej>SK59</KodLokalizacjiDocelowej>
    <KodLokalizacjiWDrodze>XMWDR</KodLokalizacjiWDrodze>
    <DataWydania> </DataWydania>
    <DataPrzyjecia> </DataPrzyjecia>
    <NrTymczasowy>8379960</NrTymczasowy>
  </TransferLine>
  <TransferLine>
    <NrWiersza>60</NrWiersza>
    <NrZapasu>5008239</NrZapasu>
    <Ilosc>15</Ilosc>
    <jednostka>SZT</jednostka>
    <IloscDoWydania>15</IloscDoWydania>
    <Status> </Status>
    <Opis>Trzpień teleskopowy</Opis>
    <KodLokalizacjiPierwotnej>3200</KodLokalizacjiPierwotnej>
    <KodLokalizacjiDocelowej>SK59</KodLokalizacjiDocelowej>
    <KodLokalizacjiWDrodze>XMWDR</KodLokalizacjiWDrodze>
    <DataWydania> </DataWydania>
    <DataPrzyjecia> </DataPrzyjecia>
    <NrTymczasowy>8379960</NrTymczasowy>
  </TransferLine>
  <TransferLine>
    <NrWiersza>70</NrWiersza>
    <NrZapasu>5027983</NrZapasu>
    <Ilosc>5</Ilosc>
    <jednostka>SZT</jednostka>
    <IloscDoWydania>5</IloscDoWydania>
    <Status> </Status>
    <Opis>Komplet do przyłącza domowego</Opis>
    <KodLokalizacjiPierwotnej>3200</KodLokalizacjiPierwotnej>
    <KodLokalizacjiDocelowej>SK59</KodLokalizacjiDocelowej>
    <KodLokalizacjiWDrodze>XMWDR</KodLokalizacjiWDrodze>
    <DataWydania> </DataWydania>
    <DataPrzyjecia> </DataPrzyjecia>
    <NrTymczasowy>8379960</NrTymczasowy>
  </TransferLine>
</TransferHeader>
