<?xml version="1.0" encoding="utf-8"?>
<TransferHeader>
  <DataKsiegowania> </DataKsiegowania>
  <KodLokalizacjiPierwotnej>3200</KodLokalizacjiPierwotnej>
  <KodLokalizacjiDocelowej>SK59</KodLokalizacjiDocelowej>
  <KodLokalizacjiWDrodze>XMWDR</KodLokalizacjiWDrodze>
  <DataWydania> </DataWydania>
  <DataPrzyjecia> </DataPrzyjecia>
  <Status> </Status>
  <Uwagi>Pilne</Uwagi>
  <NrZam>PI:22.01.20/SZPEC</NrZam>
  <NrTymczasowy>5956704</NrTymczasowy>
  <TransferLine>
    <NrWiersza>10</NrWiersza>
    <NrZapasu>5004812</NrZapasu>
    <Ilosc>2</Ilosc>
    <jednostka>SZT</jednostka>
    <IloscDoWydania>2</IloscDoWydania>
    <Status> </Status>
    <Opis>Kołnierz z odejściem</Opis>
    <KodLokalizacjiPierwotnej>3200</KodLokalizacjiPierwotnej>
    <KodLokalizacjiDocelowej>SK59</KodLokalizacjiDocelowej>
    <KodLokalizacjiWDrodze>XMWDR</KodLokalizacjiWDrodze>
    <DataWydania> </DataWydania>
    <DataPrzyjecia> </DataPrzyjecia>
    <NrTymczasowy>5956704</NrTymczasowy>
  </TransferLine>
  <TransferLine>
    <NrWiersza>20</NrWiersza>
    <NrZapasu>5004854</NrZapasu>
    <Ilosc>2</Ilosc>
    <jednostka>SZT</jednostka>
    <IloscDoWydania>2</IloscDoWydania>
    <Status> </Status>
    <Opis>Kołnierz z odejściem</Opis>
    <KodLokalizacjiPierwotnej>3200</KodLokalizacjiPierwotnej>
    <KodLokalizacjiDocelowej>SK59</KodLokalizacjiDocelowej>
    <KodLokalizacjiWDrodze>XMWDR</KodLokalizacjiWDrodze>
    <DataWydania> </DataWydania>
    <DataPrzyjecia> </DataPrzyjecia>
    <NrTymczasowy>5956704</NrTymczasowy>
  </TransferLine>
  <TransferLine>
    <NrWiersza>30</NrWiersza>
    <NrZapasu>5012726</NrZapasu>
    <Ilosc>1</Ilosc>
    <jednostka>SZT</jednostka>
    <IloscDoWydania>1</IloscDoWydania>
    <Status> </Status>
    <Opis>Łuk kołnierzowy</Opis>
    <KodLokalizacjiPierwotnej>3200</KodLokalizacjiPierwotnej>
    <KodLokalizacjiDocelowej>SK59</KodLokalizacjiDocelowej>
    <KodLokalizacjiWDrodze>XMWDR</KodLokalizacjiWDrodze>
    <DataWydania> </DataWydania>
    <DataPrzyjecia> </DataPrzyjecia>
    <NrTymczasowy>5956704</NrTymczasowy>
  </TransferLine>
  <TransferLine>
    <NrWiersza>40</NrWiersza>
    <NrZapasu>5013327</NrZapasu>
    <Ilosc>1</Ilosc>
    <jednostka>SZT</jednostka>
    <IloscDoWydania>1</IloscDoWydania>
    <Status> </Status>
    <Opis>Trójnik kołnierzowy</Opis>
    <KodLokalizacjiPierwotnej>3200</KodLokalizacjiPierwotnej>
    <KodLokalizacjiDocelowej>SK59</KodLokalizacjiDocelowej>
    <KodLokalizacjiWDrodze>XMWDR</KodLokalizacjiWDrodze>
    <DataWydania> </DataWydania>
    <DataPrzyjecia> </DataPrzyjecia>
    <NrTymczasowy>5956704</NrTymczasowy>
  </TransferLine>
  <TransferLine>
    <NrWiersza>50</NrWiersza>
    <NrZapasu>5003515</NrZapasu>
    <Ilosc>1</Ilosc>
    <jednostka>SZT</jednostka>
    <IloscDoWydania>1</IloscDoWydania>
    <Status> </Status>
    <Opis>Opaska do nawiercania HAKU</Opis>
    <KodLokalizacjiPierwotnej>3200</KodLokalizacjiPierwotnej>
    <KodLokalizacjiDocelowej>SK59</KodLokalizacjiDocelowej>
    <KodLokalizacjiWDrodze>XMWDR</KodLokalizacjiWDrodze>
    <DataWydania> </DataWydania>
    <DataPrzyjecia> </DataPrzyjecia>
    <NrTymczasowy>5956704</NrTymczasowy>
  </TransferLine>
  <TransferLine>
    <NrWiersza>60</NrWiersza>
    <NrZapasu>5003520</NrZapasu>
    <Ilosc>1</Ilosc>
    <jednostka>SZT</jednostka>
    <IloscDoWydania>1</IloscDoWydania>
    <Status> </Status>
    <Opis>Opaska do nawiercania HAKU</Opis>
    <KodLokalizacjiPierwotnej>3200</KodLokalizacjiPierwotnej>
    <KodLokalizacjiDocelowej>SK59</KodLokalizacjiDocelowej>
    <KodLokalizacjiWDrodze>XMWDR</KodLokalizacjiWDrodze>
    <DataWydania> </DataWydania>
    <DataPrzyjecia> </DataPrzyjecia>
    <NrTymczasowy>5956704</NrTymczasowy>
  </TransferLine>
</TransferHeader>
