<?xml version="1.0" encoding="utf-8"?>
<SalesHeader>
  <DocumentType>1</DocumentType>
  <DataDokumentu> </DataDokumentu>
  <NrNabywcy>107098</NrNabywcy>
  <NrOdbiorcy>107098</NrOdbiorcy>
  <DataZamowienia>2019-07-11</DataZamowienia>
  <DataKsiegowania> </DataKsiegowania>
  <DataWydania> </DataWydania>
  <Nip> </Nip>
  <KodKrajuVat>PL</KodKrajuVat>
  <Uwagi> </Uwagi>
  <NrZam>666592</NrZam>
  <NrTymczasowy>666592</NrTymczasowy>
  <SalesLine>
    <DocumentType>1</DocumentType>
    <NrWiersza>10</NrWiersza>
    <NrNabywcy>107098</NrNabywcy>
    <Typ>2</Typ>
    <Nr>5003346</Nr>
    <KodLokalizacji>SK73</KodLokalizacji>
    <Opis>Kombinacyjna zasuwa do nawier.</Opis>
    <Jednostka>SZT</Jednostka>
    <Ilosc>1</Ilosc>
    <NrTymczasowy>666592</NrTymczasowy>
    <Uwagi> </Uwagi>
  </SalesLine>
</SalesHeader>
